CHANGES.txt
LICENSE
MANIFEST.in
README.rst
RELEASE-VERSION
setup.cfg
setup.py
version.py
examples/list_myrigs.py
examples/list_scrypt.py
examples/mrrapi.cfg
examples/rig_pricing/updaterigprice.py
examples/rig_pricing/updaterigprices.py
mrrapi/__init__.py
mrrapi/mrrapi.py
mrrapi/test.py
mrrapi.egg-info/PKG-INFO
mrrapi.egg-info/SOURCES.txt
mrrapi.egg-info/dependency_links.txt
mrrapi.egg-info/entry_points.txt
mrrapi.egg-info/requires.txt
mrrapi.egg-info/top_level.txt
mrrapi/helpers/__init__.py
mrrapi/tools/__init__.py
mrrapi/tools/getallrigs.py
mrrapi/tools/list_myrigs.py
mrrapi/tools/updaterigprice.py