Metadata-Version: 1.1
Name: mrrapi
Version: 0.3.5
Summary: MinigRigRentals.com python API client and integration
Home-page: https://github.com/jcwoltz/mrrapi
Author: jcwoltz
Author-email: jwoltz@gmail.com
License: UNKNOWN
Keywords: mrr miningrigrentals api bitcoin
Platform: UNKNOWN
Classifier: Development Status :: 4 - Beta
Classifier: Programming Language :: Python
Classifier: Topic :: Office/Business :: Financial
